MANIFEST.in
VERSION
pyproject.toml
requirements.txt
setup.py
docs/source/conf.py
examples/jwks.py
examples/simple.py
unimatrix/__init__.py
unimatrix.ext.kms.egg-info/PKG-INFO
unimatrix.ext.kms.egg-info/SOURCES.txt
unimatrix.ext.kms.egg-info/dependency_links.txt
unimatrix.ext.kms.egg-info/requires.txt
unimatrix.ext.kms.egg-info/top_level.txt
unimatrix/ext/__init__.py
unimatrix/ext/kms/__init__.py
unimatrix/ext/kms/const.py
unimatrix/ext/kms/exceptions.py
unimatrix/ext/kms/joseheader.py
unimatrix/ext/kms/josesignature.py
unimatrix/ext/kms/jsonwebkey.py
unimatrix/ext/kms/jsonwebkeyset.py
unimatrix/ext/kms/jsonwebtoken.py
unimatrix/ext/kms/jwt.py
unimatrix/ext/kms/keychain.py
unimatrix/ext/kms/package.json
unimatrix/ext/kms/registry.py
unimatrix/ext/kms/truststore.py
unimatrix/ext/kms/utils.py
unimatrix/ext/kms/loaders/__init__.py
unimatrix/ext/kms/loaders/jwks.py
unimatrix/ext/kms/model/__init__.py
unimatrix/ext/kms/model/asymmetrickey.py
unimatrix/ext/kms/model/digest.py
unimatrix/ext/kms/model/ec.py
unimatrix/ext/kms/model/ellipticcurvemixin.py
unimatrix/ext/kms/model/ellipticcurveprivatekey.py
unimatrix/ext/kms/model/ellipticcurvepublickey.py
unimatrix/ext/kms/model/hmackey.py
unimatrix/ext/kms/model/key.py
unimatrix/ext/kms/model/keyversion.py
unimatrix/ext/kms/model/privatekey.py
unimatrix/ext/kms/model/publickey.py
unimatrix/ext/kms/model/rsamixin.py
unimatrix/ext/kms/model/rsaprivatekey.py
unimatrix/ext/kms/model/rsapublickey.py
unimatrix/ext/kms/model/signature.py
unimatrix/ext/kms/model/signer.py
unimatrix/ext/kms/model/symmetrickey.py
unimatrix/ext/kms/model/versionedkey.py
unimatrix/ext/kms/model/tests/__init__.py
unimatrix/ext/kms/model/tests/test_unit_digest.py
unimatrix/ext/kms/model/tests/test_unit_keyversion.py
unimatrix/ext/kms/presets/__init__.py
unimatrix/ext/kms/providers/octet.py
unimatrix/ext/kms/providers/pem.py
unimatrix/ext/kms/providers/google/__init__.py
unimatrix/ext/kms/providers/google/cryptokeyaddress.py
unimatrix/ext/kms/providers/google/hmackey.py
unimatrix/ext/kms/providers/google/keyrepository.py
unimatrix/ext/kms/tests/__init__.py
unimatrix/ext/kms/tests/basesigning.py
unimatrix/ext/kms/tests/conftest.py
