Metadata-Version: 2.1
Name: unimatrix.ext.kms
Version: 0.6.0
Summary: Abstraction layer for common cryptographic operations.
Home-page: https://gitlab.com/unimatrixone
Author: Cochise Ruhulessin
Author-email: cochise.ruhulessin@unimatrixone.io
License: UNKNOWN
Platform: UNKNOWN
Classifier: Development Status :: 4 - Beta
Classifier: Environment :: Console
Classifier: Environment :: Web Environment
Classifier: Intended Audience :: Developers
Classifier: Intended Audience :: Financial and Insurance Industry
Classifier: Intended Audience :: Healthcare Industry
Classifier: License :: Other/Proprietary License
Classifier: Operating System :: POSIX
Classifier: Operating System :: POSIX :: Linux
Classifier: Programming Language :: Python :: 3.9
Classifier: Programming Language :: Python :: 3 :: Only
Classifier: Topic :: Security
Classifier: Topic :: Security :: Cryptography
Classifier: Topic :: Software Development :: Libraries
Provides-Extra: all
Provides-Extra: google
